<?xml version="1.0" encoding="UTF-8"?>
<list xmlns:ns0="http://www.w3.org/2001/XMLSchema-instance" ns0:noNamespaceSchemaLocation="../xsd/multisell.xsd">
	<item>
		<!-- PC Commendation Points -->
		<ingredient count="444000" id="-100" />
		<!-- Adena -->
		<ingredient count="4232342" id="57" />
		<!-- Blue Eva -->
		<ingredient count="1" id="4355" />

		<!-- Agathion Seal Bracelet - Three-headed Dragon - Wind Walk -->
		<production count="1" id="20970" />
	</item>
	<item>
		<!-- PC Commendation Points -->
		<ingredient count="444000" id="-100" />
		<!-- Adena -->
		<ingredient count="4232342" id="57" />
		<!-- Blue Eva -->
		<ingredient count="1" id="4355" />

		<!-- Agathion Seal Bracelet - Ball Trapping Gnosian - Soccer Ball of Cheers, Buff of Cheers -->
		<production count="1" id="20986" />
	</item>
	<item>
		<!-- PC Commendation Points -->
		<ingredient count="444000" id="-100" />
		<!-- Adena -->
		<ingredient count="4232342" id="57" />
		<!-- Blue Eva -->
		<ingredient count="1" id="4355" />

		<!-- Agathion Seal Bracelet - Ball Trapping Orodriel - Soccer Ball of Cheers, Buff of Cheers -->
		<production count="1" id="20987" />
	</item>
	<item>
		<!-- PC Commendation Points -->
		<ingredient count="444000" id="-100" />
		<!-- Adena -->
		<ingredient count="4232342" id="57" />
		<!-- Blue Eva -->
		<ingredient count="1" id="4355" />

		<!-- Agathion Seal Bracelet - Ball Trapping Gnosian - Soccer Ball of Cheers, Buff of Cheers -->
		<production count="1" id="20989" />
	</item>
	<item>
		<!-- PC Commendation Points -->
		<ingredient count="444000" id="-100" />
		<!-- Adena -->
		<ingredient count="4232342" id="57" />
		<!-- Blue Eva -->
		<ingredient count="1" id="4355" />

		<!-- Agathion Seal Bracelet - Ball Trapping Orodriel - Soccer Ball of Cheers, Buff of Cheers -->
		<production count="1" id="20990" />
	</item>
	<item>
		<!-- PC Commendation Points -->
		<ingredient count="780000" id="-100" />
		<!-- Adena -->
		<ingredient count="6223421" id="57" />
		<!-- Blue Eva -->
		<ingredient count="1" id="4355" />

		<!-- Phoenix Agthion Seal Bracelet - Nirvana Rebirth - 7-day limited period -->
		<production count="1" id="20940" />
	</item>
	<item>
		<!-- PC Commendation Points -->
		<ingredient count="780000" id="-100" />
		<!-- Adena -->
		<ingredient count="6223421" id="57" />
		<!-- Blue Eva -->
		<ingredient count="1" id="4355" />

		<!-- Phoenix Agthion Seal Bracelet - Oriental Phoenix - 7-day limited period -->
		<production count="1" id="20941" />
	</item>
	<item>
		<!-- PC Commendation Points -->
		<ingredient count="1325000" id="-100" />
		<!-- Adena -->
		<ingredient count="16223421" id="57" />
		<!-- Blue Eva -->
		<ingredient count="1" id="4355" />

		<!-- Toy Knight Summon Whistle -->
		<production count="1" id="14061" />
	</item>
	<item>
		<!-- PC Commendation Points -->
		<ingredient count="1325000" id="-100" />
		<!-- Adena -->
		<ingredient count="16223421" id="57" />
		<!-- Blue Eva -->
		<ingredient count="1" id="4355" />

		<!-- Spirit Shaman Summon Whistle -->
		<production count="1" id="14062" />
	</item>
	<item>
		<!-- PC Commendation Points -->
		<ingredient count="1325000" id="-100" />
		<!-- Adena -->
		<ingredient count="16223421" id="57" />
		<!-- Blue Eva -->
		<ingredient count="1" id="4355" />

		<!-- Owl Monk Summon Whistle -->
		<production count="1" id="14063" />
	</item>
	<item>
		<!-- PC Commendation Points -->
		<ingredient count="1325000" id="-100" />
		<!-- Adena -->
		<ingredient count="16223421" id="57" />
		<!-- Blue Eva -->
		<ingredient count="1" id="4355" />

		<!-- Turtle Ascetic Summon Whistle -->
		<production count="1" id="14064" />
	</item>
	<item>
		<!-- PC Commendation Points -->
		<ingredient count="1325000" id="-100" />
		<!-- Adena -->
		<ingredient count="16223421" id="57" />
		<!-- Blue Eva -->
		<ingredient count="1" id="4355" />

		<!-- Steam Sledge Mount Bracelet -->
		<production count="1" id="13546" />
	</item>
	<item>
		<!-- PC Commendation Points -->
		<ingredient count="1325000" id="-100" />
		<!-- Adena -->
		<ingredient count="16223421" id="57" />
		<!-- Blue Eva -->
		<ingredient count="1" id="4355" />

		<!-- Tawny-Maned Lion Mount Bracelet -->
		<production count="1" id="13547" />
	</item>
	<item>
		<!-- PC Commendation Points -->
		<ingredient count="1325000" id="-100" />
		<!-- Adena -->
		<ingredient count="16223421" id="57" />
		<!-- Blue Eva -->
		<ingredient count="1" id="4355" />

		<!-- Jet Bike Mount Bracelet -->
		<production count="1" id="21088" />
	</item>
	<item>
		<!-- PC Commendation Points -->
		<ingredient count="1325000" id="-100" />
		<!-- Adena -->
		<ingredient count="16223421" id="57" />
		<!-- Blue Eva -->
		<ingredient count="1" id="4355" />

		<!-- White Weasel Hunting Helper Necklace -->
		<production count="1" id="13017" />
	</item>
	<item>
		<!-- PC Commendation Points -->
		<ingredient count="1325000" id="-100" />
		<!-- Adena -->
		<ingredient count="16223421" id="57" />
		<!-- Blue Eva -->
		<ingredient count="1" id="4355" />

		<!-- Fairy Princess Hunting Helper Necklace -->
		<production count="1" id="13018" />
	</item>
	<item>
		<!-- PC Commendation Points -->
		<ingredient count="1325000" id="-100" />
		<!-- Adena -->
		<ingredient count="16223421" id="57" />
		<!-- Blue Eva -->
		<ingredient count="1" id="4355" />

		<!-- Wild Beast Fighter Hunting Helper Necklace -->
		<production count="1" id="13019" />
	</item>
	<item>
		<!-- PC Commendation Points -->
		<ingredient count="1325000" id="-100" />
		<!-- Adena -->
		<ingredient count="16223421" id="57" />
		<!-- Blue Eva -->
		<ingredient count="1" id="4355" />

		<!-- Fox Shaman Hunting Helper Necklace -->
		<production count="1" id="13020" />
	</item>
	<item>
		<!-- PC Commendation Points -->
		<ingredient count="1325000" id="-100" />
		<!-- Adena -->
		<ingredient count="16223421" id="57" />
		<!-- Blue Eva -->
		<ingredient count="1" id="4355" />

		<!-- Guardian's Dragon Bugle -->
		<production count="1" id="14819" />
	</item>
</list>
